{
  "best-products": [
    {
      "id": 1,
      "code": "rv-b-01",
      "food_name": "Sate Ayam",
      "price": 3000,
      "is_ready": true,
      "satuan": "Tusuk",
      "image": "Foods_1.jpg"
    },
    {
      "id": 2,
      "code": "rv-b-01",
      "food_name": "Bakso",
      "price": 15000,
      "is_ready": true,
      "satuan": "Mangkok",
      "image": "Foods_1.jpg"
    },
    {
      "id": 3,
      "code": "rv-b-01",
      "food_name": "Martabak Manis",
      "price": 25000,
      "is_ready": true,
      "satuan": "Bungkus",
      "image": "Foods_1.jpg"
    }
  ],
  "products": [
    {
      "id": 10,
      "code": "rv-p-01",
      "food_name": "Nasi Goreng",
      "price": 12000,
      "is_ready": true,
      "satuan": "Porsi",
      "image": "Foods_1.jpg"
    },
    {
      "id": 11,
      "code": "rv-p-01",
      "food_name": "Nasi Goreng",
      "price": 12000,
      "is_ready": true,
      "satuan": "Porsi",
      "image": "nasi_goreng.jpg"
    },
    {
      "id": 12,
      "code": "rv-p-01",
      "food_name": "Nasi Goreng",
      "price": 12000,
      "is_ready": true,
      "satuan": "Porsi",
      "image": "nasi_goreng.jpg"
    },
    {
      "id": 13,
      "code": "rv-p-01",
      "food_name": "Nasi Goreng",
      "price": 12000,
      "is_ready": true,
      "satuan": "Porsi",
      "image": "nasi_goreng.jpg"
    },
    {
      "id": 14,
      "code": "rv-p-01",
      "food_name": "Sate",
      "price": 12000,
      "is_ready": true,
      "satuan": "Porsi",
      "image": "nasi_goreng.jpg"
    },
    {
      "id": 15,
      "code": "rv-p-01",
      "food_name": "Nasi Goreng",
      "price": 12000,
      "is_ready": true,
      "satuan": "Porsi",
      "image": "nasi_goreng.jpg"
    }
  ],
  "keranjang": [],
  "pesanan": []
}
